LICENSE
MANIFEST.in
README.rst
requirements.txt
setup.py
opslib/__init__.py
opslib/icsas.py
opslib/icsec2.py
opslib/icselb.py
opslib/icsexception.py
opslib/icslog.py
opslib/icsmeta.py
opslib/icsr53.py
opslib/icss3.py
opslib/icssgroup.py
opslib/icssns.py
opslib/icssqs.py
opslib/opslib.ini
opslib/zone.py
opslib.egg-info/PKG-INFO
opslib.egg-info/SOURCES.txt
opslib.egg-info/dependency_links.txt
opslib.egg-info/requires.txt
opslib.egg-info/top_level.txt
opslib/icsutils/__init__.py
opslib/icsutils/augeas.py
opslib/icsutils/cli.py
opslib/icsutils/daemon.py
opslib/icsutils/execshell.py
opslib/icsutils/icsalert.py
opslib/icsutils/jsoncli.py
opslib/icsutils/jsondiff.py
opslib/icsutils/jsonsubs.py
opslib/icsutils/misc.py
opslib/icsutils/sshkey.py
opslib/icsutils/sysconf.py
opslib/icsutils/utils.py
opslib/icsutils/configobj/__init__.py
opslib/icsutils/configobj/configobj.py
opslib/icsutils/configobj/validate.py