Metadata-Version: 1.0
Name: opslib
Version: 0.0.3.3
Summary: Library for AWS Operations
Home-page: https://github.com/henrysher/opslib
Author: Henry Huang
Author-email: henry.s.huang@gmail.com
License: Apache 2.0
Platform: UNKNOWN
Classifier: Development Status :: 2 - Pre-Alpha
Classifier: Intended Audience :: Developers
Classifier: Intended Audience :: Information Technology
Classifier: Intended Audience :: System Administrators
Classifier: License :: OSI Approved :: Apache Software License
Classifier: Natural Language :: English
Classifier: Programming Language :: Python :: 2.6
Classifier: Programming Language :: Python :: 2.7
Classifier: Topic :: System :: Installation/Setup
Classifier: Topic :: Utilities
